{
	"configurations" : 
	[
		{
			"directories" : 
			[
				{
					"build" : ".",
					"jsonFile" : "directory-.-Debug-f5ebdc15457944623624.json",
					"minimumCMakeVersion" : 
					{
						"string" : "3.28"
					},
					"projectIndex" : 0,
					"source" : ".",
					"targetIndexes" : 
					[
						0
					]
				}
			],
			"name" : "Debug",
			"projects" : 
			[
				{
					"directoryIndexes" : 
					[
						0
					],
					"name" : "1015",
					"targetIndexes" : 
					[
						0
					]
				}
			],
			"targets" : 
			[
				{
					"directoryIndex" : 0,
					"id" : "1015::@6890427a1f51a3e7e1df",
					"jsonFile" : "target-1015-Debug-bfb81b62a1d45dae08f2.json",
					"name" : "1015",
					"projectIndex" : 0
				}
			]
		}
	],
	"kind" : "codemodel",
	"paths" : 
	{
		"build" : "/Users/hanminju/Documents/Git/Project_drunken/cmake-build-debug",
		"source" : "/Users/hanminju/Documents/Git/Project_drunken"
	},
	"version" : 
	{
		"major" : 2,
		"minor" : 7
	}
}
